sam_annotator/__init__.py
sam_annotator/main.py
sam_annotator/cli/__init__.py
sam_annotator/cli/config.py
sam_annotator/cli/csv_utils.py
sam_annotator/cli/logging_utils.py
sam_annotator/cli/main.py
sam_annotator/cli/parser.py
sam_annotator/config/__init__.py
sam_annotator/config/settings.py
sam_annotator/config/shortcuts.py
sam_annotator/config/task_config.py
sam_annotator/config/validation_config.py
sam_annotator/core/__init__.py
sam_annotator/core/annotation_manager.py
sam_annotator/core/annotator.py
sam_annotator/core/annotator_Copy_Base_2.py
sam_annotator/core/annotator_base.py
sam_annotator/core/base_annotator.py
sam_annotator/core/base_predictor.py
sam_annotator/core/base_task.py
sam_annotator/core/command_manager.py
sam_annotator/core/file_manager.py
sam_annotator/core/file_manager_base.py
sam_annotator/core/memory_manager.py
sam_annotator/core/memory_manager_base.py
sam_annotator/core/memory_recovery.py
sam_annotator/core/predictor.py
sam_annotator/core/recovery_status.py
sam_annotator/core/sam_annotator.py
sam_annotator/core/session_manager.py
sam_annotator/core/validation.py
sam_annotator/core/weight_manager.py
sam_annotator/core/tasks/__init__.py
sam_annotator/core/tasks/segmentation/__init__.py
sam_annotator/core/tasks/segmentation/sam_predictor.py
sam_annotator/core/tasks/segmentation/segmentation_task.py
sam_annotator/core/tasks/segmentation/validation.py
sam_annotator/data/__init__.py
sam_annotator/data/annotation.py
sam_annotator/data/annotation_data.py
sam_annotator/data/dataset_manager.py
sam_annotator/data/exporters/__init__.py
sam_annotator/data/exporters/base_exporter.py
sam_annotator/data/exporters/coco_exporter.py
sam_annotator/data/exporters/pascal_exporter.py
sam_annotator/data/exporters/yolo_exporter.py
sam_annotator/ui/__init__.py
sam_annotator/ui/event_handler.py
sam_annotator/ui/event_handler_base.py
sam_annotator/ui/interaction_manager.py
sam_annotator/ui/window_manager.py
sam_annotator/ui/window_manager_base.py
sam_annotator-0.1.0.dist-info/licenses/LICENSE
sam_annotator-0.1.0.dist-info/METADATA
sam_annotator-0.1.0.dist-info/WHEEL
sam_annotator-0.1.0.dist-info/entry_points.txt
sam_annotator-0.1.0.dist-info/top_level.txt
sam_annotator-0.1.0.dist-info/RECORD
