Metadata-Version: 2.4
Name: sam_annotator
Version: 0.1.0
Summary: A general-purpose image annotation tool based on Segment Anything Model (SAM)
Home-page: https://github.com/pavodi-nm/sam_annotator
Author: SAM Annotator Team
Author-email: Pavodi NDOYI MANIAMFU <pavodi.mani@fingervision.biz>
License: MIT
Project-URL: Homepage, https://github.com/pavodi-nm/sam_annotator
Project-URL: Bug Tracker, https://github.com/pavodi-nm/sam_annotator/issues
Project-URL: Documentation, https://pavodi-nm.github.io/sam_annotator/
Classifier: Development Status :: 3 - Alpha
Classifier: Programming Language :: Python :: 3
Classifier: Operating System :: OS Independent
Classifier: Intended Audience :: Developers
Classifier: Intended Audience :: Science/Research
Classifier: Topic :: Scientific/Engineering :: Artificial Intelligence
Classifier: Topic :: Scientific/Engineering :: Image Processing
Requires-Python: >=3.8
License-File: LICENSE
Requires-Dist: torch>=1.7.0
Requires-Dist: opencv-python>=4.5.0
Requires-Dist: numpy>=1.19.0
Requires-Dist: segment-anything>=1.0
Requires-Dist: pandas>=1.2.0
Requires-Dist: pyyaml>=6.0
Requires-Dist: psutil>=5.9.0
Requires-Dist: requests>=2.28.0
Requires-Dist: tqdm>=4.64.0
Requires-Dist: ultralytics>=8.0.0
Provides-Extra: dev
Requires-Dist: pytest>=6.0; extra == "dev"
Requires-Dist: pytest-cov>=2.0; extra == "dev"
Requires-Dist: black>=20.8b1; extra == "dev"
Requires-Dist: isort>=5.0; extra == "dev"
Provides-Extra: docs
Requires-Dist: mkdocs>=1.4.0; extra == "docs"
Requires-Dist: mkdocs-material>=9.0.0; extra == "docs"
Requires-Dist: mkdocstrings[python]>=0.20.0; extra == "docs"
Requires-Dist: mike>=1.1.2; extra == "docs"
Dynamic: author
Dynamic: home-page
Dynamic: license-file
Dynamic: requires-python
